remla23_team17_lib/__init__.py
remla23_team17_lib/lib/__init__.py
remla23_team17_lib/lib/version_util.py
remla23_team17_lib-1.0.6.dist-info/METADATA
remla23_team17_lib-1.0.6.dist-info/WHEEL
remla23_team17_lib-1.0.6.dist-info/top_level.txt
remla23_team17_lib-1.0.6.dist-info/RECORD
