Metadata-Version: 2.1
Name: remla23-team17-lib
Version: 1.0.6
Summary: Library for retrieving repo versions
Home-page: https://github.com/remla23-team17/lib
Author: remla23-team17
Author-email: remyduijsens@gmail.com
Classifier: Development Status :: 5 - Production/Stable
Classifier: Intended Audience :: Developers
Classifier: Operating System :: OS Independent
Classifier: License :: OSI Approved :: MIT License
Classifier: Programming Language :: Python :: 3.9
